garland.py
garland-0.2.0.dist-info/DESCRIPTION.rst
garland-0.2.0.dist-info/METADATA
garland-0.2.0.dist-info/metadata.json
garland-0.2.0.dist-info/RECORD
garland-0.2.0.dist-info/top_level.txt
garland-0.2.0.dist-info/WHEEL
