Metadata-Version: 2.0
Name: garland
Version: 0.2.0
Summary: Python decorator mocking.
Home-page: https://github.com/bennylope/garland
Author: Ben Lopatin
Author-email: ben@wellfire.co
License: BSD
Keywords: garland
Platform: UNKNOWN
Classifier: Development Status :: 2 - Pre-Alpha
Classifier: Intended Audience :: Developers
Classifier: License :: OSI Approved :: BSD License
Classifier: Natural Language :: English
Classifier: Programming Language :: Python :: 2
Classifier: Programming Language :: Python :: 2.7
Classifier: Programming Language :: Python :: 3
Classifier: Programming Language :: Python :: 3.4
